{"id": 849114157, "name": "No Opinion", "username": "1st_Noopinion", "bio": "Criminal Lawyer by day..gymaholic by night. ❤️ NYC", "location": "", "url": "", "join_date": "27 Sep 2012", "join_time": "4:39 AM", "tweets": 2996, "following": 533, "followers": 105, "likes": 1967, "media": 128, "private": 0, "verified": 0, "profile_image_url": "https://pbs.twimg.com/profile_images/1059870357673443329/0sDsQGFr_400x400.jpg", "background_image": "https://pbs.twimg.com/profile_banners/849114157/1564998084/1500x500"}
