{"id": 180813868, "name": "ACR Simple Tasks", "username": "ACRSimpleTasks", "bio": "@ACRheum Simple Tasks raises awareness about rheumatic diseases & the role of rheumatologists.", "location": "", "url": "http://www.simpletasks.org", "join_date": "20 Aug 2010", "join_time": "8:12 AM", "tweets": 5893, "following": 1419, "followers": 4279, "likes": 2329, "media": 1211, "private": 0, "verified": 0, "profile_image_url": "https://pbs.twimg.com/profile_images/783268228843900928/HOhOZcOO_400x400.jpg", "background_image": "https://pbs.twimg.com/profile_banners/180813868/1567009896/1500x500"}
