{"id": 333103211, "name": "Kenya Whitaker", "username": "Agtowngal", "bio": "Mom to the twins, daughter to my parents, friend to my friends, and servant to my Lord and Savior Jesus Christ.", "location": "Arlington Tx", "url": "", "join_date": "10 Jul 2011", "join_time": "5:18 PM", "tweets": 535, "following": 1071, "followers": 49, "likes": 4858, "media": 0, "private": 1, "verified": 0, "profile_image_url": "https://pbs.twimg.com/profile_images/1074318367266349056/vfihE647_400x400.jpg", "background_image": "https://pbs.twimg.com/profile_banners/333103211/1544972896/1500x500"}
