{"id": 732424387413061633, "name": "Aleoba", "username": "AleobaMarket", "bio": "Online Market Place, Sell your Products for FREE, /encourage men and women who are selling by purchasing their products /become an affiliate / advertise", "location": "Cleveland, OH", "url": "http://aleoba.com", "join_date": "16 May 2016", "join_time": "9:15 PM", "tweets": 221, "following": 3383, "followers": 611, "likes": 372, "media": 49, "private": 0, "verified": 0, "profile_image_url": "https://pbs.twimg.com/profile_images/1050996059193786368/COnzTfG2_400x400.jpg", "background_image": "https://pbs.twimg.com/profile_banners/732424387413061633/1539473766/1500x500"}
