{"id": 398237392, "name": "Amanda Brandt", "username": "Amanda__Brandt", "bio": "@Creighton Social Media Strategist. Formerly @TheEagle and @KearneyHub. Candy enthusiast.", "location": "Omaha, NE", "url": "", "join_date": "25 Oct 2011", "join_time": "12:38 PM", "tweets": 10015, "following": 2206, "followers": 1141, "likes": 14424, "media": 756, "private": 0, "verified": 0, "profile_image_url": "https://pbs.twimg.com/profile_images/1108802226028453889/Ugrw386v_400x400.png", "background_image": "https://pbs.twimg.com/profile_banners/398237392/1485545265/1500x500"}
