{"id": 200729810, "name": "Chad H. Parker", "username": "askaamericanist", "bio": "Historian. US in the World. Author of Making the Desert Modern: Americans, Arabs, and Oil on the Saudi Frontier, 1933-1973.", "location": "Lafayette, LA", "url": "", "join_date": "9 Oct 2010", "join_time": "7:41 PM", "tweets": 148, "following": 563, "followers": 97, "likes": 144, "media": 1, "private": 0, "verified": 0, "profile_image_url": "https://pbs.twimg.com/profile_images/963920565978279936/rBdN41LO_400x400.jpg", "background_image": null}
