{"id": 3208016566, "name": "Norman369", "username": "awakening83", "bio": "we are the one infinite creator ♡ #LawOfOne #FullDisclosure #SecretSpaceProgram #CosmicDisclosure #divinecosmos", "location": "", "url": "", "join_date": "26 Apr 2015", "join_time": "6:20 AM", "tweets": 2259, "following": 291, "followers": 129, "likes": 8680, "media": 13, "private": 0, "verified": 0, "profile_image_url": "https://pbs.twimg.com/profile_images/1030107956128489478/333mHgGP_400x400.jpg", "background_image": "https://pbs.twimg.com/profile_banners/3208016566/1535040283/1500x500"}
