{"id": 31310756, "name": "Beth McGuire", "username": "bethmcg", "bio": "Middle school mom and wife of ER nurse.  National real estate news editor. Dinner conversations are diverse.", "location": "", "url": "", "join_date": "14 Apr 2009", "join_time": "7:25 PM", "tweets": 188, "following": 914, "followers": 42, "likes": 97, "media": 179, "private": 0, "verified": 0, "profile_image_url": "https://pbs.twimg.com/profile_images/837449399571742724/PDhvZBB5_400x400.jpg", "background_image": "https://pbs.twimg.com/profile_banners/31310756/1488499783/1500x500"}
