{"id": 964458547596746757, "name": "Beth Warman", "username": "BeWarm0101", "bio": "MDCPS Instructional Support Specialist South ESE Service Center @ Homestead SHS - An Individual - A Mother - ’Nothing haunts us like the things we don't say'", "location": "United States", "url": "", "join_date": "16 Feb 2018", "join_time": "3:16 AM", "tweets": 302, "following": 1105, "followers": 125, "likes": 7749, "media": 6, "private": 0, "verified": 0, "profile_image_url": "https://pbs.twimg.com/profile_images/1185360273747697669/c8hRsNwg_400x400.jpg", "background_image": "https://pbs.twimg.com/profile_banners/964458547596746757/1560308340/1500x500"}
