{"id": 2161410631, "name": "Bill Jeffrey", "username": "billjeffrey3", "bio": "Son Rise Surfing for a New Day... 71% of the earth is water! Jesus said, \"I am the way, the truth, and the life. No one comes to the Father except through Me.\"", "location": "", "url": "", "join_date": "28 Oct 2013", "join_time": "11:39 AM", "tweets": 56, "following": 109, "followers": 31, "likes": 44, "media": 0, "private": 1, "verified": 0, "profile_image_url": "https://pbs.twimg.com/profile_images/378800000661397477/320542f7961a8d83554220c328a71e2c_400x400.jpeg", "background_image": "https://pbs.twimg.com/profile_banners/2161410631/1570805241/1500x500"}
