{"id": 971098103611887616, "name": "Cecilia Hernandez 😅", "username": "CeciliaCruz033", "bio": "Don’t take things for granted because the small things are the big things💞🌷 sc// tortas1247 😅", "location": "United States", "url": "", "join_date": "6 Mar 2018", "join_time": "11:00 AM", "tweets": 66, "following": 195, "followers": 14, "likes": 686, "media": 0, "private": 0, "verified": 0, "profile_image_url": "https://pbs.twimg.com/profile_images/971099624772685824/Z2I0Udca_400x400.jpg", "background_image": "https://pbs.twimg.com/profile_banners/971098103611887616/1520363232/1500x500"}
