{"id": 14869508, "name": "Kelly Spina", "username": "cettim", "bio": "http://facebook.com/bywayofthemuse ", "location": "Mantua, NJ, USA", "url": "http://omaser.com/kelly", "join_date": "22 May 2008", "join_time": "8:27 AM", "tweets": 292, "following": 1364, "followers": 299, "likes": 78, "media": 35, "private": 0, "verified": 0, "profile_image_url": "https://pbs.twimg.com/profile_images/667513007556046850/wrc7LyDR_400x400.jpg", "background_image": "https://pbs.twimg.com/profile_banners/14869508/1447982441/1500x500"}
