{"id": 1184649024911138816, "name": "free thinker", "username": "civilengibeer", "bio": "livin rent free in yo head", "location": "", "url": "", "join_date": "16 Oct 2019", "join_time": "6:55 PM", "tweets": 7, "following": 57, "followers": 4, "likes": 10, "media": 1, "private": 0, "verified": 0, "profile_image_url": "https://pbs.twimg.com/profile_images/1184658210076217346/471IjyG2_400x400.jpg", "background_image": "https://pbs.twimg.com/profile_banners/1184649024911138816/1571279502/1500x500"}
