{"id": 832823320697565184, "name": "Deenee A Bagus", "username": "DeeneeBagus", "bio": "My Dad My Role Model....Good Governance..... Youth Activist, Dynamism.....Pray For Me If I'm No More", "location": "Kaduna Central", "url": "", "join_date": "17 Feb 2017", "join_time": "9:25 PM", "tweets": 468, "following": 600, "followers": 512, "likes": 1083, "media": 68, "private": 0, "verified": 0, "profile_image_url": "https://pbs.twimg.com/profile_images/1108278232133062656/5Mxl6rLo_400x400.jpg", "background_image": "https://pbs.twimg.com/profile_banners/832823320697565184/1561304548/1500x500"}
