{"id": 1072567082695434240, "name": "John Dettori", "username": "DettoriJohn", "bio": "Retired and not much to do.", "location": "", "url": "", "join_date": "11 Dec 2018", "join_time": "11:01 AM", "tweets": 696, "following": 66, "followers": 47, "likes": 258, "media": 1, "private": 0, "verified": 0, "profile_image_url": "https://pbs.twimg.com/profile_images/1072570456945946626/BIcSb35n_400x400.jpg", "background_image": "https://pbs.twimg.com/profile_banners/1072567082695434240/1544555699/1500x500"}
