{"id": 1935676208, "name": "Maria Diego", "username": "diego__travel", "bio": "Owner of Diego Travel and Sales Director at Marina La Bonita.", "location": "Coral Gables, FL", "url": "http://www.diegotravel.com", "join_date": "4 Oct 2013", "join_time": "3:31 PM", "tweets": 10, "following": 75, "followers": 34, "likes": 193, "media": 1, "private": 0, "verified": 0, "profile_image_url": "https://pbs.twimg.com/profile_images/1181933308252475393/sqF_h7AV_400x400.jpg", "background_image": "https://pbs.twimg.com/profile_banners/1935676208/1570629835/1500x500"}
