{"id": 282592610, "name": "Don Sisson", "username": "donsisson", "bio": "Democratic Staff Director, House Committee on Rules. Former Obama White House Staff (WHOLA).", "location": "Washington D.C.", "url": "", "join_date": "15 Apr 2011", "join_time": "7:18 AM", "tweets": 325, "following": 580, "followers": 145, "likes": 1386, "media": 15, "private": 0, "verified": 0, "profile_image_url": "https://pbs.twimg.com/profile_images/940746583276056577/7l_B8sEA_400x400.jpg", "background_image": "https://pbs.twimg.com/profile_banners/282592610/1513900822/1500x500"}
