{"id": 1209827545262280704, "name": "fatimajamal", "username": "fatimaj04772595", "bio": "Pharmacy student at R.U.C", "location": "Iraq,baghdad", "url": "", "join_date": "25 Dec 2019", "join_time": "5:25 AM", "tweets": 0, "following": 140, "followers": 3, "likes": 4, "media": 0, "private": 0, "verified": 0, "profile_image_url": "https://pbs.twimg.com/profile_images/1209833852182491137/fYQ1pIY__400x400.jpg", "background_image": "https://pbs.twimg.com/profile_banners/1209827545262280704/1577282079/1500x500"}
