{"id": 779708320265437184, "name": "Wanda Faye Baker", "username": "fayetoddbaker", "bio": "News DIY & Home Government & Politics Food & Drink", "location": "", "url": "", "join_date": "24 Sep 2016", "join_time": "8:45 AM", "tweets": 3871, "following": 574, "followers": 40, "likes": 8726, "media": 0, "private": 1, "verified": 0, "profile_image_url": "https://pbs.twimg.com/profile_images/780165901308030976/QOPtQahT_400x400.jpg", "background_image": "https://pbs.twimg.com/profile_banners/779708320265437184/1474841025/1500x500"}
