{"id": 300702831, "name": "HarmonicWave", "username": "harmonicwave4", "bio": "I despise Nazis, communist, corporatism, anti-capitalism, manipulators and all totalitarian control freaks.", "location": "", "url": "", "join_date": "17 May 2011", "join_time": "11:40 PM", "tweets": 8127, "following": 1551, "followers": 132, "likes": 722, "media": 130, "private": 0, "verified": 0, "profile_image_url": "https://pbs.twimg.com/profile_images/1206123067409195011/drSmuBme_400x400.jpg", "background_image": null}
