{"id": 47695877, "name": "Claudia", "username": "HumanOfTheMonth", "bio": "Ich nehme so lange nichts ernst, bis ich es ernst meine. Lektorin und Gelegenheitsredakteurin @t3n. Sie/She.", "location": "Hanover, Germany", "url": "https://t3n.de/pioneers/profile/claudia.wieschollek", "join_date": "16 Jun 2009", "join_time": "11:11 AM", "tweets": 757, "following": 400, "followers": 92, "likes": 9135, "media": 71, "private": 0, "verified": 0, "profile_image_url": "https://pbs.twimg.com/profile_images/1082663210996715520/84SPpSLG_400x400.jpg", "background_image": "https://pbs.twimg.com/profile_banners/47695877/1546976942/1500x500"}
