{"id": 27079577, "name": "Katherine Thompson", "username": "Irishkatherine", "bio": "PR, communications and social media professional I Arts & events manager I Love arts, culture, traveling and kitties. Originally from Ireland. #yegcomms #yegpr", "location": "Edmonton, Alberta, Canada", "url": "", "join_date": "27 Mar 2009", "join_time": "12:43 PM", "tweets": 4439, "following": 2880, "followers": 950, "likes": 14719, "media": 53, "private": 0, "verified": 0, "profile_image_url": "https://pbs.twimg.com/profile_images/536935148969668608/k5xS0SsN_400x400.jpeg", "background_image": "https://pbs.twimg.com/profile_banners/27079577/1438101021/1500x500"}
