{"id": 3437963343, "name": "Yassin Yusuf", "username": "iy_yassin", "bio": "LIFE,is a miracle itself,comes with its own surprises.It takes us forth & back,throwing us to whichever corner it wants.Great Experience always leaves an impact", "location": "", "url": "", "join_date": "24 Aug 2015", "join_time": "7:23 AM", "tweets": 645, "following": 184, "followers": 67, "likes": 1454, "media": 50, "private": 0, "verified": 0, "profile_image_url": "https://pbs.twimg.com/profile_images/851451222448107522/DDqXyMDk_400x400.jpg", "background_image": "https://pbs.twimg.com/profile_banners/3437963343/1473015437/1500x500"}
