{"id": 1148806803318288386, "name": "ChicotheCat", "username": "JamieCo59891859", "bio": "Curious but not obsessively so. 50,000 shades of gray. Our country is being run by Trump Crime Family.", "location": "", "url": "", "join_date": "9 Jul 2019", "join_time": "9:11 PM", "tweets": 868, "following": 574, "followers": 40, "likes": 637, "media": 0, "private": 0, "verified": 0, "profile_image_url": "https://pbs.twimg.com/profile_images/1148815735357132805/KUb0Tbxd_400x400.png", "background_image": null}
