{"id": 416767837, "name": "Jamie Voyles", "username": "jamie_voyles", "bio": "Assoc Professor | disease ecologist |science nerd 🤓 | advocate for #womeninSTEM #diversityinSTEM | #voyleslab | she/her", "location": "Earth", "url": "http://voyleslab.weebly.com/", "join_date": "19 Nov 2011", "join_time": "7:51 PM", "tweets": 667, "following": 1068, "followers": 605, "likes": 934, "media": 57, "private": 0, "verified": 0, "profile_image_url": "https://pbs.twimg.com/profile_images/703983113039249408/jFOGkOq9_400x400.jpg", "background_image": "https://pbs.twimg.com/profile_banners/416767837/1456677998/1500x500"}
