{"id": 2729261523, "name": "Jorge A. Medina", "username": "jamo14067", "bio": "Estudiante, crítico, libre pensador.", "location": "México DF", "url": "", "join_date": "30 Jul 2014", "join_time": "12:08 PM", "tweets": 10414, "following": 2167, "followers": 161, "likes": 13019, "media": 125, "private": 0, "verified": 0, "profile_image_url": "https://pbs.twimg.com/profile_images/1177809498116952069/w-Qg5d1L_400x400.jpg", "background_image": "https://pbs.twimg.com/profile_banners/2729261523/1569107466/1500x500"}
