{"id": 231278352, "name": "Jazmine Hughes", "username": "jazzedloon", "bio": "magazine editor", "location": "jazmine.hughes@nytimes.com", "url": "", "join_date": "27 Dec 2010", "join_time": "6:45 PM", "tweets": 23069, "following": 1009, "followers": 31640, "likes": 49837, "media": 1557, "private": 0, "verified": 0, "profile_image_url": "https://pbs.twimg.com/profile_images/1211437137129803776/9-kim181_400x400.jpg", "background_image": "https://pbs.twimg.com/profile_banners/231278352/1491969880/1500x500"}
