{"id": 16682379, "name": "Jill Warren", "username": "JillWarrenTX", "bio": "Texas lawyer and owner of five Barre3 studios in DC & VA - Georgetown, Spring Valley, Union Station, Clarendon, and Navy Yard", "location": "DC", "url": "http://www.barre3.com/", "join_date": "10 Oct 2008", "join_time": "5:22 AM", "tweets": 504, "following": 1411, "followers": 555, "likes": 267, "media": 0, "private": 1, "verified": 0, "profile_image_url": "https://pbs.twimg.com/profile_images/872195998218629120/7iBd3zK7_400x400.jpg", "background_image": null}
