{"id": 926065082974515200, "name": "John Proctor", "username": "John_Proctor68", "bio": "Wrongly accused, Dont trust thy females.", "location": "", "url": "", "join_date": "2 Nov 2017", "join_time": "5:34 AM", "tweets": 6, "following": 98, "followers": 1, "likes": 1, "media": 1, "private": 0, "verified": 0, "profile_image_url": "https://pbs.twimg.com/profile_images/926068848289353728/RuCcUn_0_400x400.jpg", "background_image": "https://pbs.twimg.com/profile_banners/926065082974515200/1509627087/1500x500"}
