{"id": 1015543369, "name": "Jo van den Broek", "username": "jovdbjo", "bio": "Likes Food, Fiction, Politics, Cats, & looking at water. No wonder I'm still not sure what to do when I grow up.", "location": "Greenwich, London, Europe", "url": "", "join_date": "16 Dec 2012", "join_time": "8:15 AM", "tweets": 3905, "following": 1813, "followers": 678, "likes": 26017, "media": 302, "private": 0, "verified": 0, "profile_image_url": "https://pbs.twimg.com/profile_images/696804042509574144/20EFm6xa_400x400.jpg", "background_image": "https://pbs.twimg.com/profile_banners/1015543369/1409344649/1500x500"}
