{"id": 832261537637203968, "name": "John R. Eakin", "username": "JREakin", "bio": "Politics. Data. Strategy. @theAAPC #2019Pollies Winner for Machine Learning/Data Analytics with @getupstream. RT ≠ Endorsement.  alum.", "location": "Austin, TX", "url": "https://jreak.in/2XdHUwX", "join_date": "16 Feb 2017", "join_time": "8:13 AM", "tweets": 5743, "following": 669, "followers": 356, "likes": 2034, "media": 184, "private": 0, "verified": 0, "profile_image_url": "https://pbs.twimg.com/profile_images/1065024095354593281/wUcZRdj1_400x400.jpg", "background_image": "https://pbs.twimg.com/profile_banners/832261537637203968/1542328698/1500x500"}
