{"id": 48087663, "name": "Samantha Pendleton", "username": "katerinfg", "bio": "Medieval re-enactor (costumer, herald, bard). Cat mom. Cust svc rep. Liberal activist. Proud Clevelander. Person w/ disabilities. Lousy housekeeper. She/her.", "location": "", "url": "", "join_date": "17 Jun 2009", "join_time": "12:44 PM", "tweets": 1027, "following": 563, "followers": 35, "likes": 884, "media": 4, "private": 0, "verified": 0, "profile_image_url": "https://pbs.twimg.com/profile_images/789137726624768000/RJsFevKu_400x400.jpg", "background_image": null}
