{"id": 822855628431433729, "name": "Kindall Tyson", "username": "kchriste817", "bio": "ASPIRING to change the face of therapy....", "location": "Houston, TX", "url": "", "join_date": "21 Jan 2017", "join_time": "9:17 AM", "tweets": 2889, "following": 250, "followers": 109, "likes": 24217, "media": 101, "private": 0, "verified": 0, "profile_image_url": "https://pbs.twimg.com/profile_images/1197396931707715584/_WbxC8IC_400x400.jpg", "background_image": "https://pbs.twimg.com/profile_banners/822855628431433729/1574316655/1500x500"}
