{"id": 2411611928, "name": "Kevin Adler", "username": "KevinAdlerMe", "bio": "* Real Estate Nerd * Animal Lover * Husband * Technology Geek * Community Leader * Honest * Trustworthy * E-Scooter Driver * Vespa Rider *", "location": "Arlington, VA", "url": "http://www.KevinAdler.Me", "join_date": "25 Mar 2014", "join_time": "3:17 PM", "tweets": 2077, "following": 173, "followers": 154, "likes": 645, "media": 114, "private": 0, "verified": 0, "profile_image_url": "https://pbs.twimg.com/profile_images/456212362458963969/WsD3xuZr_400x400.jpeg", "background_image": "https://pbs.twimg.com/profile_banners/2411611928/1397604232/1500x500"}
