{"id": 11891962, "name": "kioman", "username": "kioman", "bio": "Musician, songwriter, writer with a passion for news, design, food, science, history. My life has relocated from Manhattan to West Texas.", "location": "USA", "url": "", "join_date": "5 Jan 2008", "join_time": "4:46 PM", "tweets": 103717, "following": 4999, "followers": 3672, "likes": 127586, "media": 211, "private": 0, "verified": 0, "profile_image_url": "https://pbs.twimg.com/profile_images/402498157/IMG_0640_400x400.JPG", "background_image": "https://pbs.twimg.com/profile_banners/11891962/1480337140/1500x500"}
