{"id": 398278536, "name": "Krish O'Mara Vignarajah", "username": "KrishVignarajah", "bio": "Proud new mom, Mrs.@Collin_Omara. President & CEO @LIRSorg. Policy Director in Obama White House. Ran for MD Governor. Tweets are mine.", "location": "Gaithersburg, MD", "url": "http://www.lirs.org", "join_date": "25 Oct 2011", "join_time": "1:49 PM", "tweets": 2068, "following": 501, "followers": 5112, "likes": 1685, "media": 368, "private": 0, "verified": 0, "profile_image_url": "https://pbs.twimg.com/profile_images/1053115937682087937/iTIs13A5_400x400.jpg", "background_image": "https://pbs.twimg.com/profile_banners/398278536/1495143730/1500x500"}
