{"id": 817434881391067138, "name": "Kristin Morley", "username": "kristin_morley1", "bio": "Equality believer, Dog lover & Truth Seeker...Bowie lover & human rights fighter.", "location": "Los Angeles, CA", "url": "", "join_date": "6 Jan 2017", "join_time": "10:17 AM", "tweets": 6020, "following": 212, "followers": 43, "likes": 4666, "media": 447, "private": 0, "verified": 0, "profile_image_url": "https://pbs.twimg.com/profile_images/817437819685609472/_V3jwnCr_400x400.jpg", "background_image": "https://pbs.twimg.com/profile_banners/817434881391067138/1483727412/1500x500"}
