{"id": 16520468, "name": "Kristina Shull", "username": "kristinashull", "bio": "Immigration historian at Harvard | Soros Justice Fellow formerly at @MigrantFreedom | Creator of @Imm_Print immigration detention stories and @ClimRefStories", "location": "Cambridge, MA", "url": "", "join_date": "29 Sep 2008", "join_time": "4:32 PM", "tweets": 301, "following": 2476, "followers": 838, "likes": 999, "media": 16, "private": 0, "verified": 0, "profile_image_url": "https://pbs.twimg.com/profile_images/973289152971137024/Ntemjzw-_400x400.jpg", "background_image": "https://pbs.twimg.com/profile_banners/16520468/1520885532/1500x500"}
