{"id": 909779602012336129, "name": "frivolous beatnik", "username": "Kroenkmeister", "bio": "uwu", "location": "Grain Valley, MO", "url": "", "join_date": "18 Sep 2017", "join_time": "7:02 AM", "tweets": 1650, "following": 319, "followers": 117, "likes": 2455, "media": 123, "private": 0, "verified": 0, "profile_image_url": "https://pbs.twimg.com/profile_images/1140474548762087425/oJiO2XUO_400x400.jpg", "background_image": "https://pbs.twimg.com/profile_banners/909779602012336129/1574044034/1500x500"}
