{"id": 946955219706904576, "name": "Gretl Krooksmer", "username": "krooksmer", "bio": "Educator, spouse, mom, seething ball of impotent rage", "location": "", "url": "", "join_date": "29 Dec 2017", "join_time": "8:04 PM", "tweets": 1080, "following": 705, "followers": 67, "likes": 4803, "media": 10, "private": 0, "verified": 0, "profile_image_url": "https://pbs.twimg.com/profile_images/964502860456017920/aCQawEhA_400x400.jpg", "background_image": "https://pbs.twimg.com/profile_banners/946955219706904576/1518790375/1500x500"}
