{"id": 16413013, "name": "Larry Jebsen", "username": "lardog61", "bio": "Larry is an agent-focused, non-competing manager that emphasizes training and personalized one-on-one coaching. As such, he contributes much of his office’s suc", "location": "Anderson Twp.", "url": "", "join_date": "22 Sep 2008", "join_time": "5:55 PM", "tweets": 6104, "following": 2535, "followers": 353, "likes": 23794, "media": 0, "private": 1, "verified": 0, "profile_image_url": "https://pbs.twimg.com/profile_images/257182450/Larry_Jebsen_-_VID00023_2_400x400.jpg", "background_image": null}
