{"id": 263250514, "name": "Dre", "username": "LittleYoungDre", "bio": "London📍 #AFC Snapchat:Youngdre4 ✨ Insta:Dreyounge⭐️", "location": "", "url": "http://arsenal.com", "join_date": "9 Mar 2011", "join_time": "9:54 AM", "tweets": 4079, "following": 7159, "followers": 6561, "likes": 1743, "media": 90, "private": 0, "verified": 0, "profile_image_url": "https://pbs.twimg.com/profile_images/1110264390274691077/G-I8Ljbr_400x400.jpg", "background_image": "https://pbs.twimg.com/profile_banners/263250514/1543015324/1500x500"}
