{"id": 277380358, "name": "Liz martino", "username": "lizmartino23", "bio": "I'm 32, try to stay positive and loving the square life! Always been very hardworking and caring .....", "location": "Derby, CT", "url": "", "join_date": "5 Apr 2011", "join_time": "12:34 AM", "tweets": 78, "following": 508, "followers": 64, "likes": 237, "media": 1, "private": 0, "verified": 0, "profile_image_url": "https://pbs.twimg.com/profile_images/868667403340849153/SpNASqkh_400x400.jpg", "background_image": "https://pbs.twimg.com/profile_banners/277380358/1476822847/1500x500"}
