{"id": 118844174, "name": "Lora Elaine Jones", "username": "loraelaine", "bio": "I pray to have eyes that see the best, a heart that forgives the worst, a mind that forgets the bad and a soul that never loses its faith.", "location": "", "url": "", "join_date": "1 Mar 2010", "join_time": "2:35 PM", "tweets": 23985, "following": 1079, "followers": 266, "likes": 29543, "media": 0, "private": 1, "verified": 0, "profile_image_url": "https://pbs.twimg.com/profile_images/985420499655290880/0gQEJWD8_400x400.jpg", "background_image": "https://pbs.twimg.com/profile_banners/118844174/1509236373/1500x500"}
