{"id": 1176753957781164033, "name": "MAGA ***CULT-FORTY5*** MAGA", "username": "MAGA_JAKE_MAGA", "bio": "#MAGA / #TRUMP / #TRUMPPENCE2020 / #NRA / #LIBERALS_SUCK / #ClimateChange_is_Bullshyt / #TRUMP_2020_LANDSLIDE #Μολὼν_λαβέ", "location": "", "url": "", "join_date": "25 Sep 2019", "join_time": "12:04 AM", "tweets": 1752, "following": 2468, "followers": 1882, "likes": 8393, "media": 264, "private": 0, "verified": 0, "profile_image_url": "https://pbs.twimg.com/profile_images/1199912125801496576/Ov-V66NR_400x400.jpg", "background_image": "https://pbs.twimg.com/profile_banners/1176753957781164033/1572975222/1500x500"}
