{"id": 2749922470, "name": "Maryann Silva", "username": "MaryannSlv", "bio": "True Blue , animal rights , tango student, costume enthusiasts . Union Strong , Ward 4  Wishing you peace and prosperity . Quick fix , take me to the beach !", "location": "", "url": "", "join_date": "21 Aug 2014", "join_time": "7:25 PM", "tweets": 813, "following": 371, "followers": 109, "likes": 1436, "media": 37, "private": 0, "verified": 0, "profile_image_url": "https://pbs.twimg.com/profile_images/911288705209503744/Y7Jc3y3z_400x400.jpg", "background_image": "https://pbs.twimg.com/profile_banners/2749922470/1506103065/1500x500"}
