{"id": 2720593208, "name": "Greg Vincent", "username": "MaxFarmDM", "bio": "Stuff on farming, Maximum Farming System, Cyclones, Royals and other things.", "location": "Kansas City, MO", "url": "http://www.agspectrum.com", "join_date": "9 Aug 2014", "join_time": "6:54 PM", "tweets": 502, "following": 799, "followers": 288, "likes": 335, "media": 101, "private": 0, "verified": 0, "profile_image_url": "https://pbs.twimg.com/profile_images/793987735681830912/ET26WLBQ_400x400.jpg", "background_image": "https://pbs.twimg.com/profile_banners/2720593208/1478136366/1500x500"}
