{"id": 19223361, "name": "Judy Gonzalez", "username": "megandrewsmom", "bio": "Wife, Mother, Daughter, Sister, Conservative, Pro-Life, Seahawk Fan!", "location": "Washington (The State)", "url": "", "join_date": "19 Jan 2009", "join_time": "10:50 PM", "tweets": 2539, "following": 639, "followers": 233, "likes": 583, "media": 134, "private": 0, "verified": 0, "profile_image_url": "https://pbs.twimg.com/profile_images/1168729594217648128/5cwdf3-B_400x400.jpg", "background_image": "https://pbs.twimg.com/profile_banners/19223361/1555907890/1500x500"}
