{"id": 16291520, "name": "Meghan Hurley", "username": "megeden", "bio": "actress, writer, event planner, drinker of wine, beach goer and world traveler.", "location": "Tulsa, OK", "url": "http://www.meghanhurley.com", "join_date": "14 Sep 2008", "join_time": "8:47 PM", "tweets": 6140, "following": 679, "followers": 376, "likes": 6077, "media": 0, "private": 1, "verified": 0, "profile_image_url": "https://pbs.twimg.com/profile_images/378800000110684946/67660666104d06622be5191ff07d0b54_400x400.jpeg", "background_image": null}
