{"id": 834592014079373312, "name": "Theresa Price", "username": "MrsTheresaPrice", "bio": "School Psychologist", "location": "Marin County, CA", "url": "https://twitter.com/MrsTheresaPrice", "join_date": "22 Feb 2017", "join_time": "6:33 PM", "tweets": 48, "following": 367, "followers": 62, "likes": 1243, "media": 0, "private": 0, "verified": 0, "profile_image_url": "https://pbs.twimg.com/profile_images/1023431926252597248/5aBwErkA_400x400.jpg", "background_image": "https://pbs.twimg.com/profile_banners/834592014079373312/1487977589/1500x500"}
