{"id": 2161786746, "name": "Robert Davis", "username": "MyBushyBeard", "bio": "YouTuber | Vlogs | http://youtube.com/MyBushyBeard ", "location": "Michigan, USA", "url": "", "join_date": "28 Oct 2013", "join_time": "4:31 PM", "tweets": 263, "following": 1947, "followers": 7258, "likes": 5546, "media": 72, "private": 0, "verified": 0, "profile_image_url": "https://pbs.twimg.com/profile_images/1151745345505890304/XehIhib4_400x400.jpg", "background_image": "https://pbs.twimg.com/profile_banners/2161786746/1577457811/1500x500"}
