{"id": 257290339, "name": "Nancy Marchese", "username": "Nancy_Marchese", "bio": "Passion 4 transforming lives of kids w #autism + their families, #BCBA, #ClinicalPsychologist, #Mom, Day by Day #Persistently moving closer 2 my vision", "location": "Toronto, Ontario,  Canada", "url": "http://www.breakthroughautism.ca", "join_date": "24 Feb 2011", "join_time": "7:27 PM", "tweets": 3340, "following": 1595, "followers": 1278, "likes": 6112, "media": 190, "private": 0, "verified": 0, "profile_image_url": "https://pbs.twimg.com/profile_images/378800000543565443/b1ca2e1e1bc759aedfd190edbcc3ff20_400x400.jpeg", "background_image": null}
