{"id": 511177773, "name": "natalie carignan", "username": "nataliecarignan", "bio": "1st grade teacher in Bexley, Ohio.", "location": "", "url": "", "join_date": "1 Mar 2012", "join_time": "5:40 PM", "tweets": 730, "following": 358, "followers": 209, "likes": 1110, "media": 71, "private": 0, "verified": 0, "profile_image_url": "https://pbs.twimg.com/profile_images/378800000230212312/bb5ead17434bd4cf78ba9a1e85ab0f68_400x400.jpeg", "background_image": "https://pbs.twimg.com/profile_banners/511177773/1454866203/1500x500"}
