{"id": 800973530200469504, "name": "PatriceTS", "username": "PatriceThatche2", "bio": "...mother, partner, professor, resister. raised in Alaska, converted to Californian, currently working in California, living in Ashland Oregon. #demclassic", "location": "Ashland, OR", "url": "", "join_date": "22 Nov 2016", "join_time": "12:05 AM", "tweets": 4200, "following": 219, "followers": 122, "likes": 41930, "media": 19, "private": 0, "verified": 0, "profile_image_url": "https://pbs.twimg.com/profile_images/1207178200851181568/4jKuJLbY_400x400.jpg", "background_image": "https://pbs.twimg.com/profile_banners/800973530200469504/1576648687/1500x500"}
