{"id": 329746828, "name": "Petra MA, RDN/LD, IBCLC", "username": "PetraNutrition", "bio": "Assistant Prof @NSU 🦈 Maternal- child nutrition🤱& public health strategist. ♥of coffee, fitness & family. Way too into matching family shirts. Views = 💯 me.", "location": "Oklahoma City, OK", "url": "http://nutritionbypetra.com", "join_date": "5 Jul 2011", "join_time": "8:22 AM", "tweets": 5341, "following": 1201, "followers": 733, "likes": 2412, "media": 487, "private": 0, "verified": 0, "profile_image_url": "https://pbs.twimg.com/profile_images/453166104391598080/1rcTQ0_t_400x400.jpeg", "background_image": "https://pbs.twimg.com/profile_banners/329746828/1379882659/1500x500"}
