{"id": 2648777701, "name": "Karl Phillips", "username": "phillkark", "bio": "cartographer, historical geographer", "location": "", "url": "http://dyngeo.com", "join_date": "15 Jul 2014", "join_time": "10:16 AM", "tweets": 22034, "following": 58, "followers": 160, "likes": 5830, "media": 556, "private": 0, "verified": 0, "profile_image_url": "https://pbs.twimg.com/profile_images/502991455581777920/1GX9-lUU_400x400.jpeg", "background_image": "https://pbs.twimg.com/profile_banners/2648777701/1408757738/1500x500"}
