{"id": 62836560, "name": "PORT", "username": "PORTrestaurant", "bio": "North American Bistro, Bar & Community Gathering Spot. Follow on Instagram: portrestaurant. Second restaurant : @mapleleaftavern Leslieville, East Toronto", "location": "Bay Ridges, Pickering, Ontario", "url": "http://www.portrestaurant.ca", "join_date": "4 Aug 2009", "join_time": "7:50 AM", "tweets": 5476, "following": 675, "followers": 1421, "likes": 1928, "media": 531, "private": 0, "verified": 0, "profile_image_url": "https://pbs.twimg.com/profile_images/884822460012605441/jua4KTcN_400x400.jpg", "background_image": "https://pbs.twimg.com/profile_banners/62836560/1513253241/1500x500"}
