{"id": 31194708, "name": "Michael J. MacKenzie", "username": "profmjmack", "bio": "Dad. repatriated 🇨🇦 country mouse in city shoes. @CRC_CRC Canada Research Chair on Child Well-Being. Professor @McGillu #firstgen opinions frequently flawed.", "location": "Montréal, QC ", "url": "http://www.childwellbeing.org", "join_date": "14 Apr 2009", "join_time": "11:56 AM", "tweets": 2613, "following": 1860, "followers": 1355, "likes": 6621, "media": 59, "private": 0, "verified": 0, "profile_image_url": "https://pbs.twimg.com/profile_images/902780859085873152/7X566BiQ_400x400.jpg", "background_image": "https://pbs.twimg.com/profile_banners/31194708/1504077013/1500x500"}
