{"id": 284221122, "name": "Andy Paul", "username": "realAndyPaul", "bio": "B2B Sales Strategist, Speaker & Author | Host of Accelerate! (@Inc top podcast)", "location": "San Diego, California", "url": "http://www.andypaul.com/planner", "join_date": "18 Apr 2011", "join_time": "2:42 PM", "tweets": 48177, "following": 386, "followers": 16217, "likes": 3431, "media": 19500, "private": 0, "verified": 0, "profile_image_url": "https://pbs.twimg.com/profile_images/1195047883667468289/XZXygGrJ_400x400.jpg", "background_image": "https://pbs.twimg.com/profile_banners/284221122/1573757264/1500x500"}
