{"id": 276482293, "name": "Axel Schumacher", "username": "Rekamux", "bio": "Intersectional feminism, ethical polyamory, embedded systems, white cis-pan man, he/his/him, allying daily", "location": "Oakland, CA", "url": "http://axelschumacher.com", "join_date": "3 Apr 2011", "join_time": "6:01 AM", "tweets": 1629, "following": 329, "followers": 67, "likes": 3555, "media": 22, "private": 0, "verified": 0, "profile_image_url": "https://pbs.twimg.com/profile_images/699403953549619200/hb5nB6OS_400x400.jpg", "background_image": null}
