{"id": 77868827, "name": "Richard A. Longoria", "username": "richardlongoria", "bio": "\"The test of our progress is not whether we add more to the abundance of those who have much; it is whether we provide enough for those who have too little.\"", "location": "McAllen, TX", "url": "", "join_date": "27 Sep 2009", "join_time": "4:53 PM", "tweets": 14375, "following": 47, "followers": 22, "likes": 46, "media": 0, "private": 1, "verified": 0, "profile_image_url": "https://pbs.twimg.com/profile_images/881017133492310017/yQOn0Rjr_400x400.jpg", "background_image": "https://pbs.twimg.com/profile_banners/77868827/1555037675/1500x500"}
