{"id": 1055167193820905482, "name": "Rochelle Guillou", "username": "RochelleGuillo1", "bio": "", "location": "", "url": "http://www.algorand.com", "join_date": "24 Oct 2018", "join_time": "11:40 AM", "tweets": 51, "following": 115, "followers": 37, "likes": 869, "media": 0, "private": 0, "verified": 0, "profile_image_url": "https://pbs.twimg.com/profile_images/1138188373284315136/QemLHm9G_400x400.png", "background_image": "https://pbs.twimg.com/profile_banners/1055167193820905482/1560200016/1500x500"}
