{"id": 14454719, "name": "RobertScottThompson", "username": "RST_PhD", "bio": "Composer of music.  \"My work is utterly phonometrical.\"  Follow on!", "location": "Planet Earth", "url": "https://www.facebook.com/RSTAmbient/", "join_date": "20 Apr 2008", "join_time": "1:25 PM", "tweets": 16992, "following": 981, "followers": 1520, "likes": 62979, "media": 1095, "private": 0, "verified": 0, "profile_image_url": "https://pbs.twimg.com/profile_images/2050399674/Gold_small_400x400.jpg", "background_image": "https://pbs.twimg.com/profile_banners/14454719/1404578310/1500x500"}
