{"id": 322650936, "name": "Rob Lantz", "username": "RWLantz", "bio": "Christ Follower, Husband, Father, Former Marine, Co-founder of Cloudframe.", "location": "NoVa", "url": "", "join_date": "23 Jun 2011", "join_time": "7:39 AM", "tweets": 774, "following": 290, "followers": 106, "likes": 1024, "media": 70, "private": 0, "verified": 0, "profile_image_url": "https://pbs.twimg.com/profile_images/916740260348006400/t7YlSRU-_400x400.jpg", "background_image": "https://pbs.twimg.com/profile_banners/322650936/1484743912/1500x500"}
