{"id": 725852929861644288, "name": "Shawn Treston", "username": "ShawnRTreston", "bio": "Husband, Dad, HS Teacher, Army Intel Sergeant Vet, IU Alum, Basketball Coach, Former AD, Football Coach & Super Nintendo Gangster.", "location": "Round Rock, TX", "url": "", "join_date": "28 Apr 2016", "join_time": "6:03 PM", "tweets": 41, "following": 74, "followers": 12, "likes": 120, "media": 0, "private": 0, "verified": 0, "profile_image_url": "https://pbs.twimg.com/profile_images/976576200234749957/A45RwZ6F_400x400.jpg", "background_image": "https://pbs.twimg.com/profile_banners/725852929861644288/1490651154/1500x500"}
