{"id": 9676342, "name": "Sheri Daunheimer", "username": "Sher_d", "bio": "Hmmmm, what can I say ??!!! I try to always live life to the fullest!!", "location": "Boston", "url": "http://facebook.com/sheridaunheimer", "join_date": "24 Oct 2007", "join_time": "10:39 PM", "tweets": 3501, "following": 2092, "followers": 320, "likes": 2349, "media": 228, "private": 0, "verified": 0, "profile_image_url": "https://pbs.twimg.com/profile_images/942301653792968704/NUBnqb2t_400x400.jpg", "background_image": "https://pbs.twimg.com/profile_banners/9676342/1472609074/1500x500"}
