{"id": 790730972, "name": "Cyndi Sides Lawson", "username": "SidesLawson", "bio": "Christian wife, hometown Tuscaloosa, Al, UA BS & 3 MAs, Special Ed Teacher, Cosmetologist, retired. Now am artist, gardener, conservative & a wicked baker.", "location": "Alabama", "url": "", "join_date": "29 Aug 2012", "join_time": "8:26 PM", "tweets": 51, "following": 85, "followers": 13, "likes": 626, "media": 0, "private": 0, "verified": 0, "profile_image_url": "https://pbs.twimg.com/profile_images/817436991017144321/0sNsOpRo_400x400.jpg", "background_image": null}
