{"id": 464274198, "name": "Sophie Kurz", "username": "SophKurz", "bio": "Northeastern University '20 Belmont High School '15", "location": "", "url": "", "join_date": "14 Jan 2012", "join_time": "5:59 PM", "tweets": 1173, "following": 405, "followers": 165, "likes": 2650, "media": 0, "private": 1, "verified": 0, "profile_image_url": "https://pbs.twimg.com/profile_images/1092541645743181826/q_IxY-UG_400x400.jpg", "background_image": "https://pbs.twimg.com/profile_banners/464274198/1447210697/1500x500"}
