{"id": 406695706, "name": "Peachy Dory - We’re all Earthlings", "username": "sosaithi", "bio": "🤡👆Anti-American👆 It's class warfare.Not Blue vs Red. Not Right vs Left. Not Conservative vs Liberal. It's Rich can never have enough, the poor have too much.", "location": "                    Left Coast", "url": "", "join_date": "6 Nov 2011", "join_time": "6:17 PM", "tweets": 45537, "following": 4028, "followers": 2421, "likes": 52178, "media": 2581, "private": 0, "verified": 0, "profile_image_url": "https://pbs.twimg.com/profile_images/1184648393877942272/YLGtd-im_400x400.jpg", "background_image": "https://pbs.twimg.com/profile_banners/406695706/1563241123/1500x500"}
