{"id": 1174758754014941184, "name": "StopCrimesoftheEnvironment 🍑", "username": "stopECOCIDEnow", "bio": "Our existence on Earth is a shared miracle; let’s respect that. ♻️☮️", "location": "", "url": "", "join_date": "19 Sep 2019", "join_time": "11:55 AM", "tweets": 3156, "following": 337, "followers": 53, "likes": 5744, "media": 52, "private": 0, "verified": 0, "profile_image_url": "https://pbs.twimg.com/profile_images/1174841369774514177/thpTiMCI_400x400.jpg", "background_image": null}
