{"id": 4718516121, "name": "Allan Domb", "username": "TeamDomb", "bio": "Philadelphia City Councilmember At-Large. @PHLCouncil let's get to work!", "location": "Philadelphia, PA", "url": "http://www.phlcouncil.com/allandomb", "join_date": "5 Jan 2016", "join_time": "1:46 PM", "tweets": 1056, "following": 221, "followers": 3516, "likes": 369, "media": 182, "private": 0, "verified": 0, "profile_image_url": "https://pbs.twimg.com/profile_images/877246379856449537/F4y8NHyT_400x400.jpg", "background_image": "https://pbs.twimg.com/profile_banners/4718516121/1452097471/1500x500"}
