{"id": 2448695690, "name": "Kathleen Dempster", "username": "thedempstar", "bio": "Person interested in the world. Believer in education, equality and the environment.", "location": "", "url": "", "join_date": "16 Apr 2014", "join_time": "8:21 PM", "tweets": 239, "following": 191, "followers": 31, "likes": 1597, "media": 7, "private": 0, "verified": 0, "profile_image_url": "https://pbs.twimg.com/profile_images/456650729990537218/EgQXlX7n_400x400.jpeg", "background_image": "https://pbs.twimg.com/profile_banners/2448695690/1397708667/1500x500"}
