{"id": 1216192950, "name": "Tristan Irvine", "username": "TIrvine38", "bio": "Millersville Graduate Government and Business. Inside Sales Rep. for Septodont. “The Juice was Worth the Squeeze”", "location": "", "url": "", "join_date": "24 Feb 2013", "join_time": "10:21 AM", "tweets": 10244, "following": 331, "followers": 243, "likes": 2832, "media": 378, "private": 0, "verified": 0, "profile_image_url": "https://pbs.twimg.com/profile_images/1202437043089027072/1hp9n8n5_400x400.jpg", "background_image": "https://pbs.twimg.com/profile_banners/1216192950/1575518328/1500x500"}
