{"id": 31591349, "name": "Tracie Davis", "username": "tracielyndavis", "bio": "Mother to 2 beautiful boys, wife, vegan, Ob/Gyn, bleeding heart liberal, diehard fan of women's soccer and lover of beer.", "location": "San Diego, CA", "url": "", "join_date": "15 Apr 2009", "join_time": "6:32 PM", "tweets": 1639, "following": 659, "followers": 141, "likes": 507, "media": 62, "private": 0, "verified": 0, "profile_image_url": "https://pbs.twimg.com/profile_images/555599037442052096/QVZgjo3K_400x400.jpeg", "background_image": null}
