{"id": 1145890442531278848, "name": "TrumpdaTraitor", "username": "TraitorTrumpda", "bio": "Anybody but Trump 2020  I just don't get Trump supporters, seriously, how fucking stupid, racist, & oblivious are you to the dumb shit this idiot spews daily???", "location": "Ohio", "url": "", "join_date": "1 Jul 2019", "join_time": "8:02 PM", "tweets": 1763, "following": 325, "followers": 24, "likes": 4360, "media": 597, "private": 0, "verified": 0, "profile_image_url": "https://pbs.twimg.com/profile_images/1156331226686509056/8GsAJoPf_400x400.jpg", "background_image": null}
