{"id": 1183576364953280512, "name": "TyAnon⭐️⭐️⭐️", "username": "Trx88Ty", "bio": "Twitter should have left my first account alone, coming back with vengeance... Christ follower, Husband, Father, Son, American. Qanon & Pizzagate", "location": "", "url": "", "join_date": "13 Oct 2019", "join_time": "7:53 PM", "tweets": 535, "following": 0, "followers": 304, "likes": 0, "media": 28, "private": 0, "verified": 0, "profile_image_url": "https://pbs.twimg.com/profile_images/1183576948666187778/40yNJ4-q_400x400.jpg", "background_image": "https://pbs.twimg.com/profile_banners/1183576364953280512/1571021710/1500x500"}
