{"id": 2332242336, "name": "Uri Ort", "username": "uri_ort", "bio": "Business Psychologist / Adjunct @nyuniversity / Co-founder @deepersignals /Personality researcher / https://bit.ly/2t5KB6b ", "location": "New York, USA", "url": "http://deepersignals.com", "join_date": "7 Feb 2014", "join_time": "10:29 AM", "tweets": 999, "following": 1852, "followers": 1202, "likes": 1277, "media": 315, "private": 0, "verified": 0, "profile_image_url": "https://pbs.twimg.com/profile_images/956186678342938624/mEInCwbl_400x400.jpg", "background_image": "https://pbs.twimg.com/profile_banners/2332242336/1413356534/1500x500"}
