{"id": 838861702754074624, "name": "Respectable Nickname", "username": "YachtRockFriday", "bio": "John's Twitter BFF   Drew Garabo Live, Star Wars, Disney, Funko, Lego, Stand Up", "location": "Inside Johns Lunchbox, Tampa", "url": "", "join_date": "6 Mar 2017", "join_time": "1:19 PM", "tweets": 9605, "following": 321, "followers": 236, "likes": 35913, "media": 1334, "private": 0, "verified": 0, "profile_image_url": "https://pbs.twimg.com/profile_images/860590480056348675/aEYThjcD_400x400.jpg", "background_image": "https://pbs.twimg.com/profile_banners/838861702754074624/1507417964/1500x500"}
